hello_claudiu_package/__init__.py
hello_claudiu_package/hello.py
hello_claudiu_package-0.3.0.dist-info/METADATA
hello_claudiu_package-0.3.0.dist-info/WHEEL
hello_claudiu_package-0.3.0.dist-info/top_level.txt
hello_claudiu_package-0.3.0.dist-info/RECORD
