Metadata-Version: 2.1
Name: hello-claudiu-package
Version: 0.3.0
Summary: first_package
Home-page: UNKNOWN
Author: Claudiu
Author-email: claudiucostea1998@gmail.com
License: UNKNOWN
Platform: UNKNOWN
